[
    {
        "id": 1,
        "background": "/src/assets/category/bg1.png",
        "title": "Маски для лица"
    },
    {
        "id": 2,
        "background": "/src/assets/category/bg2.png",
        "title": "Тканевые маски для лица"
    },
    {
        "id": 3,
        "background": "/src/assets/category/bg3.png",
        "title": "Сухие маски для лица"
    },
    {
        "id": 4,
        "background": "/src/assets/category/bg4.png",
        "title": "Маски-скрабы"
    },
    {
        "id": 5,
        "background": "/src/assets/category/bg5.png",
        "title": "Скрабы для лица"
    }
]